data_search_engine/__init__.py
data_search_engine/app.py
data_search_engine-1.1.3.dist-info/METADATA
data_search_engine-1.1.3.dist-info/WHEEL
data_search_engine-1.1.3.dist-info/top_level.txt
data_search_engine-1.1.3.dist-info/RECORD
