Metadata-Version: 2.1
Name: data-search-engine
Version: 1.1.3
Summary: A Python-based data search and visualization engine.
Home-page: https://github.com/Siatek98/data_search_engine
Author: Siatek98
Classifier: Programming Language :: Python :: 3
Classifier: License :: OSI Approved :: MIT License
Classifier: Operating System :: OS Independent
Requires-Python: >=3.6
Requires-Dist: pandas
Requires-Dist: matplotlib
Requires-Dist: fredapi
Requires-Dist: pyperclip
Requires-Dist: yfinance
Requires-Dist: requests
Requires-Dist: reportlab
Requires-Dist: openpyxl
Requires-Dist: eurostat
